ml_rest/__init__.py
ml_rest/api.py
ml_rest-1.0.3.dist-info/LICENSE
ml_rest-1.0.3.dist-info/METADATA
ml_rest-1.0.3.dist-info/WHEEL
ml_rest-1.0.3.dist-info/top_level.txt
ml_rest-1.0.3.dist-info/RECORD
